[
  {
    "url": "https://career.programmers.co.kr/job_positions/14301",
    "hash": "cb34f3983e63804f09dfc2ed918f1d58",
    "status": "active"
  },
  {
    "url": "https://career.programmers.co.kr/job_positions/14300",
    "hash": "cb34f3983e63804f09dfc2ed918f1d58",
    "status": "active"
  },
  {
    "url": "https://career.programmers.co.kr/job_positions/14302",
    "hash": "cb34f3983e63804f09dfc2ed918f1d58",
    "status": "active"
  },
  {
    "url": "https://www.wanted.co.kr/wd/192130",
    "hash": "e86e116845e3887e9cdee61bac91fec1",
    "status": "deactive"
  },
  {
    "url": "https://career.programmers.co.kr/job_positions/11369",
    "hash": "cb34f3983e63804f09dfc2ed918f1d58",
    "status": "deactive"
  }
]